dislocs/__init__.py
dislocs/dislocs.cpython-311-darwin.so
dislocs-0.1.2.dist-info/METADATA
dislocs-0.1.2.dist-info/WHEEL
dislocs-0.1.2.dist-info/licenses/LICENSE
dislocs-0.1.2.dist-info/RECORD
