Metadata-Version: 2.2
Name: dislocs
Version: 0.1.2
Summary: A Python C extension for calculating displacement, stress and strian based on rectangular and triangular dislocation elements (RDE and TDE) in elastic half space.
Keywords: okada,dislocation,geophysics,rde,tde
Author-Email: Zelong Guo <zelong.guo@outlook.com>
License: GPL-3.0
Classifier: Programming Language :: Python :: 3
Classifier: Programming Language :: Python :: 3.11
Classifier: Programming Language :: Python :: 3.12
Requires-Python: >=3.11
Requires-Dist: numpy>=2.0.0
